Metadata-Version: 2.1
Name: vDataAPI
Version: 1.4.1
Summary: vData.PL - API Client in Python
Home-page: https://gitlab.com/hscode/vdataapi-python/
Author: HSCode.PL
License: MIT
Keywords: vData.pl,HSCode.PL,API
Platform: UNKNOWN
Classifier: Development Status :: 5 - Production/Stable
Classifier: Intended Audience :: Developers
Classifier: Topic :: Software Development
Classifier: License :: OSI Approved :: MIT License
Classifier: Programming Language :: Python :: 3
Classifier: Programming Language :: Python :: 3.4
Classifier: Programming Language :: Python :: 3.5
Classifier: Programming Language :: Python :: 3.6
Classifier: Programming Language :: Python :: 3.7
Classifier: Programming Language :: Python :: 3.8
Classifier: Programming Language :: Python :: 3.9
Classifier: Natural Language :: Polish
Classifier: Natural Language :: English
